{
  "developer-tool": {
    "name": "Developer Tool",
    "repo_url": "https://github.com/yourusername/developer-tool",
    "type": "Open Source",
    "description": "A CLI tool that simplifies common development tasks.",
    "technologies": [
      "Node.js",
      "TypeScript",
      "Commander.js"
    ],
    "monetization_strategy": "Open-source (brand building)",
    "status": "Planned",
    "priority": 5,
    "problem": "Developers repeat the same setup tasks for every new project.",
    "solution": "A CLI that automates project scaffolding and configuration.",
    "target_audience": [
      "Solo developers",
      "Open source maintainers"
    ],
    "mission_statement": "Reduce time from idea to coding.",
    "blocked_by": "Finishing current SaaS project first"
  },
  "mobile-app": {
    "name": "Mobile App",
    "repo_url": "https://github.com/yourusername/mobile-app",
    "type": "Mobile App",
    "description": "A companion mobile app for the SaaS product.",
    "technologies": [
      "React Native",
      "Expo",
      "TypeScript"
    ],
    "monetization_strategy": "Included with SaaS subscription",
    "status": "Planned",
    "priority": 3,
    "problem": "Users want to access the SaaS on mobile.",
    "solution": "Native mobile app with core functionality.",
    "target_audience": [
      "Existing SaaS customers"
    ],
    "mission_statement": "Bring the tool everywhere.",
    "blocked_by": "SaaS web app needs to be complete first"
  }
}
